Workbook

Sheet DCF Model
B2: Chevron Corporation
H3: 2020 | I3: 2021 | J3: 2022 | K3: 2023 | L3: 2024 | M3: 2025 | N3: 2026 | O3: 2027 | P3: 2028 | Q3: 2029 | R3: 2030 | S3: 2031 | T3: 2032 | U3: 2033 | V3: 2034
A5: X | B5: Overview
B6: Company Ticker | C6: CVX
B7: Stock Price | C7: 186.76
B8: Implied Stock Price | C8: =F90 -> 192.0338
B9: Delta | C9: =IF(C8="","-",C8/C7-1) -> 0.028238405
B10: Scenario | C10: Base
A12: X | B12: Assumptions
C14: WORST CASE | D14: BASE CASE | E14: BEST CASE | F14: Rationale
B15: Revenue Growth % | C15: -0.02 | D15: 0.04 | E15: 0.07 | F15: Worst: ~$52 WTI, oversupply; Base: ~$67 WTI + 2-3% vol growth (mgmt guidance); Best: ~$80 WTI + Permian/Guyana outperformance
B16: EBIT margin % | C16: 0.07 | D16: 0.135 | E16: 0.17 | F16: Historical range: -6% (2020) to 16% (2022); 2023A: 13%, 2024A: 9.3%; Base reflects mid-cycle normalisation
B17: Tax % | C17: 0.32 | D17: 0.3 | E17: 0.28 | F17: 2024A: 35.5% (elevated one-off); normalised historical avg 27-30%; small but legitimate lever
B18: D&A and Capex are set as fixed dollar values below — more realistic for an oil major whose cost base is driven by assets, not revenue
B19: D&A - Base year amount | C19: 16500 | D19: 17500 | E19: 18500 | F19: Anchored to 2024A: $17.3bn. Worst: slight decline as assets deplete without reinvestment; Best: higher from Guyana/Permian asset base build
B20: D&A growth rate | C20: 0.005 | D20: 0.01 | E20: 0.015 | F20: Low fixed growth — depletion schedule drives D&A, not revenue. 2020-2024 avg growth: ~0% (range $16.3-19.5bn)
B21: Capex - Base year amount | C21: 14000 | D21: 15500 | E21: 17000 | F21: CVX guided $14.5-15.5bn/yr. Worst: capex discipline/cuts at low prices; Best: increased investment in Guyana + Permian growth
B22: Capex growth rate | C22: 0.005 | D22: 0.015 | E22: 0.025 | F22: Modest real growth reflecting asset expansion; disciplined in worst case
B23: WACC | C23: 0.1039 | D23: =WACC!E40 -> 0.0911 | E23: 0.0796 | F23: See WACC tab — CAPM build-up: Ke ~9.5%, Kd ~3.15%, E/V ~93.5%
B24: Terminal Growth Rate | C24: 0.015 | D24: 0.02 | E24: 0.025 | F24: Must be < WACC. Anchored to long-run nominal GDP (~2%); worst reflects energy transition structural decline risk
B26: Active Scenario Values
B27: Column1 | C27: Column2
B28: Revenue growth % | C28: =IF($C$10="Worst",C15,IF($C$10="Best",E15,D15)) -> 0.04
B29: EBIT Margin % | C29: =IF($C$10="Worst",C16,IF($C$10="Best",E16,D16)) -> 0.135
B30: Tax % | C30: =IF($C$10="Worst",C17,IF($C$10="Best",E17,D17)) -> 0.3
B31: D&A - Base year ($mn) | C31: =IF($C$10="Worst",C19,IF($C$10="Best",E19,D19)) -> 17500
B32: D&A Growth % | C32: =IF($C$10="Worst",C20,IF($C$10="Best",E20,D20)) -> 0.01
B33: Capex - Base year ($mn) | C33: =IF($C$10="Worst",C21,IF($C$10="Best",E21,D21)) -> 15500
B34: Capex Growth % | C34: =IF($C$10="Worst",C22,IF($C$10="Best",E22,D22)) -> 0.015
B35: WACC | C35: =IF($C$10="Worst",C23,IF($C$10="Best",E23,D23)) -> 0.0911
B36: TGR | C36: =IF($C$10="Worst",C24,IF($C$10="Best",E24,D24)) -> 0.02
A38: X | B38: Income Statement
B40: Revenue | H40: ='Income Statement'!B5 -> 94692 | I40: ='Income Statement'!C5 -> 162465 | J40: ='Income Statement'!D5 -> 246252 | K40: ='Income Statement'!E5 -> 200949 | L40: ='Income Statement'!F5 -> 202792 | M40: =L40*(1+$C$28) -> 210903.68 | N40: =M40*(1+$C$28) -> 219339.83 | O40: =N40*(1+$C$28) -> 228113.42 | P40: =O40*(1+$C$28) -> 237237.96 | Q40: =P40*(1+$C$28) -> 246727.48 | R40: =Q40*(1+$C$28) -> 256596.57 | S40: =R40*(1+$C$28) -> 266860.44 | T40: =S40*(1+$C$28) -> 277534.85 | ... V40: =U40*(1+$C$28) -> 300181.7
B41: % growth | H41: - | I41: =I40/H40-1 -> 0.71572044 | J41: =J40/I40-1 -> 0.51572339 | K41: =K40/J40-1 -> -0.18397008 | L41: =L40/K40-1 -> 0.0091714813 | M41: =M40/L40-1 -> 0.04 | N41: =N40/M40-1 -> 0.04 | O41: =O40/N40-1 -> 0.04 | P41: =P40/O40-1 -> 0.04 | ... V41: =V40/U40-1 -> 0.04
B43: EBIT | H43: ='Income Statement'!B18 -> -6097 | I43: ='Income Statement'!C18 -> 16180 | J43: ='Income Statement'!D18 -> 39950 | K43: ='Income Statement'!E18 -> 26229 | L43: ='Income Statement'!F18 -> 18917 | M43: =M40*$C$29 -> 28471.997 | N43: =N40*$C$29 -> 29610.877 | O43: =O40*$C$29 -> 30795.312 | P43: =P40*$C$29 -> 32027.124 | Q43: =Q40*$C$29 -> 33308.209 | R43: =R40*$C$29 -> 34640.538 | S43: =S40*$C$29 -> 36026.159 | T43: =T40*$C$29 -> 37467.205 | ... V43: =V40*$C$29 -> 40524.529
B44: % sales | H44: =H43/H$40 -> -0.064387699 | I44: =I43/I$40 -> 0.099590681 | J44: =J43/J$40 -> 0.16223218 | K44: =K43/K$40 -> 0.13052566 | L44: =L43/L$40 -> 0.093282772 | M44: =M43/M$40 -> 0.135 | N44: =N43/N$40 -> 0.135 | O44: =O43/O$40 -> 0.135 | ... V44: =V43/V$40 -> 0.135
B46: Tax | H46: ='Income Statement'!B23 -> -1892 | I46: ='Income Statement'!C23 -> 5950 | J46: ='Income Statement'!D23 -> 14066 | K46: ='Income Statement'!E23 -> 8173 | L46: ='Income Statement'!F23 -> 9757 | M46: =M43*$C$30 -> 8541.599 | N46: =N43*$C$30 -> 8883.263 | O46: =O43*$C$30 -> 9238.5935 | P46: =P43*$C$30 -> 9608.1373 | Q46: =Q43*$C$30 -> 9992.4628 | R46: =R43*$C$30 -> 10392.161 | S46: =S43*$C$30 -> 10807.848 | T46: =T43*$C$30 -> 11240.162 | ... V46: =V43*$C$30 -> 12157.359
B47: % tax rate | H47: =H46/H$43 -> 0.31031655 | I47: =I46/I$43 -> 0.36773795 | J47: =J46/J$43 -> 0.35209011 | K47: =K46/K$43 -> 0.31160166 | L47: =L46/L$43 -> 0.51577946 | M47: =M46/M43 -> 0.3 | N47: =N46/N43 -> 0.3 | O47: =O46/O43 -> 0.3 | P47: =P46/P43 -> 0.3 | Q47: =Q46/Q43 -> 0.3 | R47: =R46/R43 -> 0.3 | S47: =S46/S43 -> 0.3 | T47: =T46/T43 -> 0.3 | ... V47: =V46/V43 -> 0.3
B49: EBIAT (or NOPAT) | H49: =H43-H46 -> -4205 | I49: =I43-I46 -> 10230 | J49: =J43-J46 -> 25884 | K49: =K43-K46 -> 18056 | L49: =L43-L46 -> 9160 | M49: =M43-M46 -> 19930.398 | N49: =N43-N46 -> 20727.614 | O49: =O43-O46 -> 21556.718 | ... V49: =V43-V46 -> 28367.171
B50: % sales | H50: =H49/H$40 -> -0.04440713 | I50: =I49/I$40 -> 0.062967408 | J50: =J49/J$40 -> 0.10511184 | K50: =K49/K$40 -> 0.089853644 | L50: =L49/L$40 -> 0.045169435 | M50: =M49/M$40 -> 0.0945 | N50: =N49/N$40 -> 0.0945 | O50: =O49/O$40 -> 0.0945 | ... V50: =V49/V$40 -> 0.0945
A53: X | B53: Cash Flow Statement
B55: Plus: Depriciation and Amortization | H55: ='Cash Flow Statement'!B6 -> 19508 | I55: ='Cash Flow Statement'!C6 -> 17925 | J55: ='Cash Flow Statement'!D6 -> 16319 | K55: ='Cash Flow Statement'!E6 -> 17326 | L55: ='Cash Flow Statement'!F6 -> 17282 | M55: =$C$31*(1+$C$32)^1 -> 17675 | N55: =$C$31*(1+$C$32)^2 -> 17851.75 | O55: =$C$31*(1+$C$32)^3 -> 18030.267 | P55: =$C$31*(1+$C$32)^4 -> 18210.57 | Q55: =$C$31*(1+$C$32)^5 -> 18392.676 | R55: =$C$31*(1+$C$32)^6 -> 18576.603 | S55: =$C$31*(1+$C$32)^7 -> 18762.369 | T55: =$C$31*(1+$C$32)^8 -> 18949.992 | U55: =$C$31*(1+$C$32)^9 -> 19139.492 | V55: =$C$31*(1+$C$32)^10 -> 19330.887
B56: % sales | H56: =H55/H$40 -> 0.20601529 | I56: =I55/I$40 -> 0.11033146 | J56: =J55/J$40 -> 0.066269513 | K56: =K55/K$40 -> 0.086220882 | L56: =L55/L$40 -> 0.085220324 | M56: =M55/M$40 -> 0.083806029 | N56: =N55/N$40 -> 0.081388548 | O56: =O55/O$40 -> 0.079040801 | ... V56: =V55/V$40 -> 0.064397288
B58: Less: Capex | H58: ='Cash Flow Statement'!B18 -> -8922 | I58: ='Cash Flow Statement'!C18 -> -8056 | J58: ='Cash Flow Statement'!D18 -> -11974 | K58: ='Cash Flow Statement'!E18 -> -15829 | L58: ='Cash Flow Statement'!F18 -> -16448 | M58: =$C$33*(1+$C$34)^1 -> 15732.5 | N58: =$C$33*(1+$C$34)^2 -> 15968.487 | O58: =$C$33*(1+$C$34)^3 -> 16208.015 | P58: =$C$33*(1+$C$34)^4 -> 16451.135 | Q58: =$C$33*(1+$C$34)^5 -> 16697.902 | R58: =$C$33*(1+$C$34)^6 -> 16948.371 | S58: =$C$33*(1+$C$34)^7 -> 17202.596 | T58: =$C$33*(1+$C$34)^8 -> 17460.635 | U58: =$C$33*(1+$C$34)^9 -> 17722.545 | V58: =$C$33*(1+$C$34)^10 -> 17988.383
B59: % sales | H59: =H58/H$40 -> -0.094221265 | I59: =I58/I$40 -> -0.049586065 | J59: =J58/J$40 -> -0.048624986 | K59: =K58/K$40 -> -0.078771231 | L59: =L58/L$40 -> -0.081107736 | M59: =M58/M$40 -> 0.074595664 | N59: =N58/N$40 -> 0.072802499 | O59: =O58/O$40 -> 0.071052439 | ... V59: =V58/V$40 -> 0.059924982
B61: Less: Changes in Working Capital | H61: ='Cash Flow Statement'!B10 -> -1652 | I61: ='Cash Flow Statement'!C10 -> -1361 | J61: ='Cash Flow Statement'!D10 -> 2125 | K61: ='Cash Flow Statement'!E10 -> -3185 | L61: ='Cash Flow Statement'!F10 -> 1211 | M61: =M40*M62 -> -1141.9173 | N61: =N40*N62 -> -1187.594 | O61: =O40*O62 -> -1235.0977 | P61: =P40*P62 -> -1284.5017 | Q61: =Q40*Q62 -> -1335.8817 | R61: =R40*R62 -> -1389.317 | S61: =S40*S62 -> -1444.8897 | T61: =T40*T62 -> -1502.6853 | ... V61: =V40*V62 -> -1625.3044
B62: % sales | H62: =H61/H$40 -> -0.017446036 | I62: =I61/I$40 -> -0.0083771889 | J62: =J61/J$40 -> 0.0086293715 | K62: =K61/K$40 -> -0.015849793 | L62: =L61/L$40 -> 0.005971636 | M62: =AVERAGE($H$62:$L$62) -> -0.0054144019 | N62: =AVERAGE($H$62:$L$62) -> -0.0054144019 | O62: =AVERAGE($H$62:$L$62) -> -0.0054144019 | P62: =AVERAGE($H$62:$L$62) -> -0.0054144019 | Q62: =AVERAGE($H$62:$L$62) -> -0.0054144019 | R62: =AVERAGE($H$62:$L$62) -> -0.0054144019 | S62: =AVERAGE($H$62:$L$62) -> -0.0054144019 | T62: =AVERAGE($H$62:$L$62) -> -0.0054144019 | ... V62: =AVERAGE($H$62:$L$62) -> -0.0054144019
A65: X | B65: Discounted Cash Flow Statement
B67: EBIAT (or NOPAT) | M67: =M49 -> 19930.398 | N67: =N49 -> 20727.614 | O67: =O49 -> 21556.718 | P67: =P49 -> 22418.987 | Q67: =Q49 -> 23315.746 | R67: =R49 -> 24248.376 | S67: =S49 -> 25218.311 | T67: =T49 -> 26227.044 | ... V67: =V49 -> 28367.171
B68: Plus: Depriciation and Amortization | M68: =M55 -> 17675 | N68: =N55 -> 17851.75 | O68: =O55 -> 18030.267 | P68: =P55 -> 18210.57 | Q68: =Q55 -> 18392.676 | R68: =R55 -> 18576.603 | S68: =S55 -> 18762.369 | T68: =T55 -> 18949.992 | ... V68: =V55 -> 19330.887
B69: Less: Capex | M69: =M58 -> 15732.5 | N69: =N58 -> 15968.487 | O69: =O58 -> 16208.015 | P69: =P58 -> 16451.135 | Q69: =Q58 -> 16697.902 | R69: =R58 -> 16948.371 | S69: =S58 -> 17202.596 | T69: =T58 -> 17460.635 | ... V69: =V58 -> 17988.383
B70: Less: Change in Working Capital | M70: =M61 -> -1141.9173 | N70: =N61 -> -1187.594 | O70: =O61 -> -1235.0977 | P70: =P61 -> -1284.5017 | Q70: =Q61 -> -1335.8817 | R70: =R61 -> -1389.317 | S70: =S61 -> -1444.8897 | T70: =T61 -> -1502.6853 | ... V70: =V61 -> -1625.3044
B72: Free Cash Flow (FCF) | M72: =M67+M68-M69-M70 -> 23014.815 | N72: =N67+N68-N69-N70 -> 23798.47 | O72: =O67+O68-O69-O70 -> 24614.069 | P72: =P67+P68-P69-P70 -> 25462.924 | Q72: =Q67+Q68-Q69-Q70 -> 26346.402 | R72: =R67+R68-R69-R70 -> 27265.925 | S72: =S67+S68-S69-S70 -> 28222.974 | T72: =T67+T68-T69-T70 -> 29219.086 | ... V72: =V67+V68-V69-V70 -> 31334.979
B74: Discount Period | M74: 1 | N74: =M74+1 -> 2 | O74: =N74+1 -> 3 | P74: =O74+1 -> 4 | Q74: =P74+1 -> 5 | R74: =Q74+1 -> 6 | S74: =R74+1 -> 7 | T74: =S74+1 -> 8 | U74: =T74+1 -> 9 | V74: =U74+1 -> 10
B75: Discount Factor | M75: =1/(1+$C$35)^M74 -> 0.91650628 | N75: =1/(1+$C$35)^N74 -> 0.83998376 | O75: =1/(1+$C$35)^O74 -> 0.76985039 | P75: =1/(1+$C$35)^P74 -> 0.70557271 | Q75: =1/(1+$C$35)^Q74 -> 0.64666182 | R75: =1/(1+$C$35)^R74 -> 0.59266962 | S75: =1/(1+$C$35)^S74 -> 0.54318543 | T75: =1/(1+$C$35)^T74 -> 0.49783285 | ... V75: =1/(1+$C$35)^V74 -> 0.41817151
B76: PV of FCF | M76: =M72*M75 -> 21093.222 | N76: =N72*N75 -> 19990.328 | O76: =O72*O75 -> 18949.15 | P76: =P72*P75 -> 17965.944 | Q76: =Q72*Q75 -> 17037.212 | R76: =R72*R75 -> 16159.686 | S76: =S72*S75 -> 15330.308 | T76: =T72*T75 -> 14546.221 | ... V76: =V72*V75 -> 13103.396
B79: Terminal Value | F79: =V72*(1+$C$36)/($C$35-$C$36) -> 449531.35
B80: PV of Terminal Value | F80: =F79*V75 -> 187981.2
B82: Sum of PV of FCF | F82: =SUM(M76:V76) -> 167980.22
B83: Enterprise Value | F83: =F80+F82 -> 355961.42
B85: Less: Net Debt (2024A) | F85: ='Balance Sheet'!G32+'Balance Sheet'!G37+'Balance Sheet'!G38-'Balance Sheet'!G7 -> 6064
B86: Less: Minority Interest (2024A) | F86: ='Balance Sheet'!G51 -> 972
B87: Equity Value | F87: =F83-F85-F86 -> 348925.42
B89: Diluted Outstanding Shares (mn) | F89: ='Income Statement'!F31 -> 1817
B90: Implied Share Price | F90: =IFERROR(F87/F89,"-") -> 192.0338

Sheet WACC
B2: WACC Calculation
A4: X | B4: Cost of Equity - CAPM: Ke = Rf + Beta * Market Risk Premium
B5: Column1 | C5: Column2 | D5: Column3 | E5: Column4
B6: Inputs | C6: Value | D6: Range/Sense Check | E6: Source
B7: Risk-Free Rate (Rf) | C7: 0.043 | D7: 4.0 - 4.5% | E7: 10-Year US Treasury yield, Feb 2026
B8: Beta | C8: 0.95 | D8: 0.85 - 1.05 | E8: Bloomberg 5-year monthly regression vs S&P 500; CVX is less volatile than market
B9: Market Risk Premium (MRP) | C9: 0.055 | D9: 5.0 - 6.0% | E9: Damodaran implied ERP, Jan 2026 (US market)
B11: Cost of Equity (Ke) | C11: =C7+(C8*C9) -> 0.09525 | D11: Rf + Beta * MRP
A13: X | B13: Cost of Debt - Kd (after tax) = Pre-tax Kd * (1 - Tax rate)
B14: Column1 | C14: Column2 | D14: Column3 | E14: Column4
B15: Inputs | C15: Value | D15: Range/Sense Check | E15: Source
B16: Pre-tax Cost of Debt (Kd) | C16: 0.045 | D16: 4.0 - 5.0% | E16: CVX Aa2/AA- rated; blended YTM on outstanding bonds (Bloomberg)
B17: Tax Rate | C17: =IF('DCF Model'!$C$10="Worst",'DCF Model'!C17,IF('DCF Model'!$C$10="Best",'DCF Model'!E17,'DCF Model'!D17)) -> 0.3 | D17: 28 - 32% | E17: Normalised effective tax rate — consistent with DCF base case assumption
B19: Cost of Debt (Kd) | C19: =C16*(1-C17) -> 0.0315 | D19: Kd * (1 - Tax Rate)
A21: X | B21: Capital Structure
B22: Column1 | C22: Column2 | D22: Column3 | E22: Column4
B23: Inputs | C23: Value ($mn) | D23: Weight | E23: Source
B24: Market Capitalization (Equity) | C24: 339422 | E24: 1,817mm diluted shares × $186.76 current price | Update manually if price changes
B25: Total Debt (2024A — STD + LTD + Leases) | C25: ='Balance Sheet'!G32+'Balance Sheet'!G37+'Balance Sheet'!G38 -> 23742 | D25: Short-Term Debt + Long-Term Debt + LT Leases | E25: Linked from Balance Sheet tab (rows 32 + 37 + 38, 2024A) | Updates automatically
B26: Memo: Book Value of Equity (2024A) | C26: ='Balance Sheet'!G52 -> 160242 | D26: For reference only — WACC uses market cap above | E26: Linked from Balance Sheet tab (row 52, 2024A) | Market cap used for WACC weights, not book
B27: Total Capital (E + D) | C27: =C24+C25 -> 363164
B28: Weight of Equity (E/V) | C28: =C24/$C$27 -> 0.93462458 | E28: Equity-heavy capital structure; CVX runs conservative leverage
B29: Weight of Debt (D/V) | C29: =C25/$C$27 -> 0.065375423 | E29: Debt ~10.7% of total capital at market values
A31: X | B31: WACC
B33: WACC | C33: =C28*C11+C29*C19 -> 0.091082317 | D33: (E/V × Ke) + (D/V × Kd) | E33: Base case: ~9.11% — consistent with DCF Model assumption. Adjust Rf, Beta or ERP to flex.
A35: X | B35: WACC Sensitivity - WACC v/s Beta
B36: Column1 | C36: Column2 | D36: Column3 | E36: Column4 | F36: Column5 | G36: Column6
B37: WACC / Beta | C37: β = 0.80 | D37: β = 0.90 | E37: β = 0.95 | F37: β = 1.00 | G37: β = 1.10
B38: MRP = 4.5% | C38: 0.0759 | D38: 0.0801 | E38: 0.0822 | F38: 0.0843 | G38: 0.0885
B39: MRP = 5.0% | C39: 0.0796 | D39: 0.0843 | E39: 0.0866 | F39: 0.089 | G39: 0.0937
B40: MRP = 5.5% | C40: 0.0834 | D40: 0.0885 | E40: 0.0911 | F40: 0.0937 | G40: 0.0988
B41: MRP = 6.0% | C41: 0.0871 | D41: 0.0927 | E41: 0.0955 | F41: 0.0983 | G41: 0.1039
B42: MRP = 6.5% | C42: 0.0908 | D42: 0.0969 | E42: 0.1 | F42: 0.103 | G42: 0.1091
B44: Yellow cell = base case (β=0.95, ERP=5.5%) → WACC ≈ 9.11% | Blue text = hardcoded inputs | Black = formulas

Sheet Data >>

Sheet Income Statement
A1: CHEVRON CORPORATION (CVX) — INCOME STATEMENT
A2: Bloomberg Consensus | Figures in USD Millions (except per share data and %)
A3: In Millions USD | B3: 2020 | C3: 2021 | D3: 2022 | E3: 2023 | F3: 2024
A4: REVENUE
A5: Total Revenue | B5: 94692 | C5: 162465 | D5: 246252 | E5: 200949 | F5: 202792
A7: COSTS & EXPENSES
A8: Cost of Revenue | B8: 11067 | C8: 11718 | D8: 12742 | E8: 12842 | F8: 13387
A9: Purchased Crude Oil & Products | B9: 52148 | C9: 92249 | D9: 145416 | E9: 119196 | F9: 119206
A10: Operating Expenses | B10: 20323 | C10: 20726 | D10: 24714 | E10: 24887 | F10: 27464
A11: Selling, General & Administrative | B11: 4213 | C11: 4014 | D11: 4312 | E11: 4141 | F11: 4834
A12: Depreciation, Depletion & Amortization | B12: 19508 | C12: 17925 | D12: 16319 | E12: 17326 | F12: 17282
A13: Exploration Expense | B13: 1537 | C13: 538 | D13: 960 | E13: 934 | F13: 1068
A14: Other Tax Expenses | B14: 2839 | C14: 3963 | D14: 4032 | E14: 4220 | F14: 4716
A15: Total Costs & Other Deductions | B15: 102145 | C15: 140826 | D15: 196578 | E15: 171365 | F15: 175286
A17: OPERATING RESULTS
A18: Operating Income | B18: -6097 | C18: 16180 | D18: 39950 | E18: 26229 | F18: 18917
A19: Interest Expense (Income), Net | B19: 697 | C19: 712 | D19: 516 | E19: 469 | F19: 594
A20: Other Income (Expense), Net | B20: -693 | C20: -1202 | D20: -1950 | E20: 1038 | F20: -1784
A21: Income from Joint Ventures | B21: -472 | C21: 5657 | D21: 8585 | E21: 5131 | F21: 4596
A22: Pre-Tax Income | B22: -7453 | C22: 21639 | D22: 49674 | E22: 29584 | F22: 27506
A23: Income Tax Expense | B23: -1892 | C23: 5950 | D23: 14066 | E23: 8173 | F23: 9757
A24: Tax Rate (%) | B24: 25.4 | C24: 27.5 | D24: 28.32 | E24: 27.63 | F24: 35.47
A25: Minority Interest | B25: -18 | C25: 64 | D25: 143 | E25: 42 | F25: 88
A26: Net Income | B26: -5543 | C26: 15689 | D26: 35465 | E26: 21369 | F26: 17661
A27: Net Income Avail. to Common | B27: -368 | C27: 15608 | D27: 36542 | E27: 24693 | F27: 18256
A29: PER SHARE DATA
A30: Basic Weighted Avg. Shares | B30: 1870 | C30: 1916 | D30: 1931 | E30: 1873 | F30: 1810
A31: Diluted Weighted Avg. Shares | B31: 1870 | C31: 1920 | D31: 1940 | E31: 1880 | F31: 1817
A32: Diluted EPS | B32: -2.96 | C32: 8.14 | D32: 18.28 | E32: 11.36 | F32: 9.72
A33: Dividend per Share | B33: 5.16 | C33: 5.31 | D33: 5.68 | E33: 6.04 | F33: 6.52
A35: SUPPLEMENTAL METRICS
A36: EBITDA | B36: =B18+B12 -> 13411 | C36: =C18+C12 -> 34105 | D36: =D18+D12 -> 56269 | E36: =E18+E12 -> 43555 | F36: =F18+F12 -> 36199
A37: Adjusted Net Income | B37: 1822 | C37: 14916 | D37: 36542 | E37: 24693 | F37: 18634
A38: Adjusted Diluted EPS | B38: -0.2 | C38: 8.13 | D38: 18.83 | E38: 13.13 | F38: 10.05
A39: Free Cash Flow | B39: 1655 | C39: 21131 | D39: 37628 | E39: 19780 | F39: 15044
A41: Source: Bloomberg Terminal, 02/10/2026, CVX US Equity

Sheet Cash Flow Statement
A1: CHEVRON CORPORATION (CVX) — CASH FLOW STATEMENT
A2: Bloomberg Consensus | Figures in USD Millions (except per share data)
A3: In Millions USD | B3: 2020 | C3: 2021 | D3: 2022 | E3: 2023 | F3: 2024
A4: CASH FROM OPERATING ACTIVITIES
A5: Net Income | B5: -5543 | C5: 15689 | D5: 35465 | E5: 21369 | F5: 17661
A6: Depreciation & Amortization | B6: 19508 | C6: 17925 | D6: 16319 | E6: 17326 | F6: 17282
A7: Gain or Loss on Disposal of Assets | B7: -760 | C7: -1021 | D7: -550 | E7: -138 | F7: -1685
A8: Other Non-Cash Items | B8: 141 | C8: 1192 | D8: 13 | E8: 1038 | F8: -1784
A9: Cash Contributions to Employee Pension Plans | B9: -1213 | C9: -1751 | D9: -1322 | E9: -1120 | F9: -844
A10: Change in Working Capital | B10: -1652 | C10: -1361 | D10: 2125 | E10: -3185 | F10: 1211
A11: Foreign Exchange Gain Loss | B11: 619 | C11: -7 | D11: -412 | E11: 578 | F11: -629
A12: Equity in Earnings of Affiliates | B12: 2015 | C12: -1998 | D12: -4730 | E12: -885 | F12: -366
A13: Deferred Taxes | B13: 1036 | C13: 118 | D13: 486 | E13: 436 | F13: 429
A14: Dry Hole Expense | B14: 0 | C14: 0 | D14: 0 | E14: 0 | F14: 0
A15: Cash Flow from Operations | B15: 10577 | C15: 29187 | D15: 49602 | E15: 35609 | F15: 31492
A17: CASH FROM INVESTING ACTIVITIES
A18: Capital Expenditures | B18: -8922 | C18: -8056 | D18: -11974 | E18: -15829 | F18: -16448
A19: Sale of Assets | B19: 2968 | C19: 1791 | D19: 2635 | E19: 669 | F19: 7704
A20: Net Repayment (Borrowing) of Loans by Equity Affiliates | B20: -1419 | C20: 401 | D20: -24 | E20: -302 | F20: -233
A21: Other Investing Activities | B21: -384 | C21: 400 | D21: 93 | E21: -127 | F21: -237
A22: Cash Flow from Investing | B22: -6965 | C22: -5865 | D22: -12108 | E22: -15232 | F22: -8936
A24: CASH FROM FINANCING ACTIVITIES
A25: Change in Long-Term Debt | B25: 6819 | C25: -7364 | D25: -8742 | E25: -4190 | F25: -1300
A26: Proceeds from Issuances of Long-Term Debt | B26: 12308 | C26: 0 | D26: 0 | E26: 150 | F26: 478
A27: Dividends Paid | B27: -9651 | C27: -10179 | D27: -10968 | E27: -11336 | F27: -11801
A28: Increase/Decrease in Borrowings | B28: 7470 | C28: -12936 | D28: -8479 | E28: -4055 | F28: 3568
A29: Net Borrowings (Repayments) of Short-Term Obligations | B29: 651 | C29: -5572 | D29: 263 | E29: 135 | F29: 4866
A30: Other | B30: -24 | C30: -36 | D30: -114 | E30: -40 | F30: -195
A31: Cash Flow from Financing | B31: -3736 | C31: -23113 | D31: -24978 | E31: -30109 | F31: -23472
A33: SUPPLEMENTAL & FREE CASH FLOW
A34: Net Changes in Cash | B34: -174 | C34: 58 | D34: 12326 | E34: -9846 | F34: -1013
A35: Cash & Cash Equivalents (BOP) | B35: 6911 | C35: 6737 | D35: 6795 | E35: 19121 | F35: 9275
A36: Cash & Cash Equivalents (EOP) | B36: 6737 | C36: 6795 | D36: 19121 | E36: 9275 | F36: 8262
A37: Free Cash Flow | B37: 1655 | C37: 21131 | D37: 37628 | E37: 19780 | F37: 15044
A38: Free Cash Flow per Share | B38: 0.89 | C38: 11.03 | D38: 19.49 | E38: 10.56 | F38: 8.31
A39: Net Share Buybacks | B39: -1531 | C39: 38 | D39: -5417 | E39: -14678 | F39: -15044
A40: Income Taxes Paid | B40: 2987 | C40: 4355 | D40: 9148 | E40: 10416 | F40: 8458
A41: Interest on Debt (Net of Capitalized Interest) | B41: 720 | C41: 699 | D41: 525 | E41: 465 | F41: 587
A42: Operational Cash Flow excl. Working Capital | B42: 12229 | C42: 30548 | D42: 47477 | E42: 38794 | F42: 30281
A43: Total Capital Expenditures | B43: 13499 | C43: 11720 | D43: 18524 | E43: 15829 | F43: 16448
A45: Source: Bloomberg Terminal, 02/10/2026, CVX US Equity

Sheet Balance Sheet
A1: CHEVRON CORPORATION (CVX) — BALANCE SHEET
A2: Bloomberg Consensus Actuals (2020–2024) | USD Millions | Year-end 31 December
B4: In Millions USD | C4: 2020A | D4: 2021A | E4: 2022A | F4: 2023A | G4: 2024A | H4: Notes
A5: ASSETS
A6: Current Assets
B7: Cash & Cash Equivalents | C7: 9342 | D7: 5686 | E7: 5596 | F7: 5640 | G7: 17678
B8: Marketable Securities | C8: 53 | D8: 63 | E8: 31 | F8: 35 | G8: 4
B9: Accounts Receivable | C9: 15050 | D9: 13325 | E9: 11471 | F9: 18419 | G9: 20456
B10: Inventories — Crude Oil & Products | C10: 3383 | D10: 3722 | E10: 3576 | F10: 4248 | G10: 5866
B11: Inventories — Chemicals | C11: 487 | D11: 492 | E11: 457 | F11: 565 | G11: 515
B12: Inventories — Materials & Supplies | C12: 1834 | D12: 1634 | E12: 1643 | F12: 1982 | G12: 1866
B13: Other Current Assets | C13: 3872 | D13: 3407 | E13: 3304 | F13: 2849 | G13: 3739
B14: Total Current Assets | C14: 34021 | D14: 28329 | E14: 26078 | F14: 33738 | G14: 50343
A16: Non-Current Assets
B17: Long-Term Receivables | C17: 1942 | D17: 1511 | E17: 589 | F17: 603 | G17: 1069
B18: Property, Plant & Equipment (Net) | C18: 169207 | D18: 150494 | E18: 156618 | F18: 146961 | G18: 143591 | H18: Net of accumulated depreciation
B19: Accumulated Depreciation | C19: 171037 | D19: 176228 | E19: 188614 | F19: 189084 | G19: 184194 | H19: Memo: gross PP&E less net PP&E
B20: Other Investments & Affiliates | C20: 35546 | D20: 38688 | E20: 39052 | F20: 40696 | G20: 45238 | H20: Equity method investments incl. CPChem JV
B21: Deferred Charges & Other Assets | C21: 6766 | D21: 10532 | E21: 11950 | F21: 12384 | G21: 12310
B22: Goodwill | C22: 4518 | D22: 4463 | E22: 4402 | F22: 4385 | G22: 4722 | H22: Primarily from legacy acquisitions
B23: Assets Held for Sale | C23: 1863 | D23: 3411 | E23: 1101 | F23: 768 | G23: 436
B24: Total Non-Current Assets | C24: 219842 | D24: 209099 | E24: 213712 | F24: 205797 | G24: 207366
B25: TOTAL ASSETS | C25: 253863 | D25: 237428 | E25: 239790 | F25: 239535 | G25: 257709
A27: LIABILITIES & EQUITY
A28: Current Liabilities
B29: Accounts Payable | C29: 13953 | D29: 14103 | E29: 10950 | F29: 16454 | G29: 18955
B30: Accrued Expenses | C30: 4927 | D30: 6589 | E30: 7812 | F30: 6972 | G30: 7486
B31: Accrued Taxes | C31: 1628 | D31: 1554 | E31: 921 | F31: 1700 | G31: 4381
B32: Short-Term Debt | C32: 5726 | D32: 3282 | E32: 1548 | F32: 256 | G32: 1964
B33: Other Taxes Payable | C33: 937 | D33: 1002 | E33: 952 | F33: 1409 | G33: 1422
B34: Total Current Liabilities | C34: 27171 | D34: 26530 | E34: 22183 | F34: 26791 | G34: 34208
A36: Non-Current Liabilities | O36: Net debt | P36: =G32+G37+G38 -> 23742
B37: Long-Term Debt | C37: 28733 | D37: 23691 | E37: 42767 | F37: 31113 | G37: 21375 | P37: =P36-G7 -> 6064
B38: LT Capital Lease Obligations | C38: 127 | D38: 282 | E38: 447 | F38: 449 | G38: 403
B39: Deferred Tax Liabilities | C39: 15921 | D39: 13688 | E39: 12569 | F39: 14665 | G39: 17131
B40: Reserves for Employee Benefits | C40: 6654 | D40: 7866 | E40: 9217 | F40: 6248 | G40: 4357 | H40: Pension & post-retirement obligations
B41: Other Non-Current Liabilities | C41: 19742 | D41: 20445 | E41: 20328 | F41: 20778 | G41: 20396 | H41: Incl. asset retirement obligations
B42: Total Non-Current Liabilities | C42: 71050 | D42: 65690 | E42: 85881 | F42: 72804 | G42: 63259
B43: Total Liabilities | C43: 98221 | D43: 92220 | E43: 107064 | F43: 99595 | G43: 97467
A45: Shareholders' Equity
B46: Common Stock | C46: 1832 | D46: 1832 | E46: 1832 | F46: 1832 | G46: 1832 | H46: Par value; shares outstanding relatively stable
B47: Additional Paid-In Capital | C47: 17112 | D47: 17265 | E47: 16829 | F47: 17282 | G47: 18660
B48: Retained Earnings | C48: 180987 | D48: 174945 | E48: 160377 | F48: 165546 | G48: 190024 | H48: Key driver; reflects cumulative net income less dividends
B49: Accumulated Other Comprehensive Loss | C49: -3544 | D49: -4990 | E49: -5612 | F49: -3889 | G49: -2798 | H49: Primarily pension & FX translation adjustments
B50: Unearned Compensation | C50: -240 | D50: -240 | E50: -240 | F50: -240 | G50: -240
B51: Minority Interest | C51: 1034 | D51: 1008 | E51: 595 | F51: 803 | G51: 972 | H51: Non-controlling interests in subsidiaries
B52: Total Shareholders' Equity | C52: 155642 | D52: 145221 | E52: 132283 | F52: 139940 | G52: 160242
B53: TOTAL LIABILITIES & EQUITY | C53: 253863 | D53: 237428 | E53: 239790 | F53: 239535 | G53: 257709
A55: KEY BALANCE SHEET RATIOS & CREDIT METRICS
B56: Metric | C56: 2020A | D56: 2021A | E56: 2022A | F56: 2023A | G56: 2024A | H56: Formula / Notes
B57: Gross Debt ($mm) | C57: 34459 | D57: 26973 | E57: 44315 | F57: 31369 | G57: 23339 | H57: Short-term debt + long-term debt + capital leases
B58: Net Debt ($mm) | C58: 25064 | D58: 21224 | E58: 38688 | F58: 25694 | G58: 5438 | H58: Gross debt less cash & equivalents
B59: Current Ratio | C59: 1.25 | D59: 1.07 | E59: 1.18 | F59: 1.26 | G59: 1.47 | H59: Current assets / current liabilities
B60: Debt / Equity | C60: 0.22 | D60: 0.19 | E60: 0.34 | F60: 0.22 | G60: 0.15 | H60: Total debt / total shareholders' equity
B61: Debt / Total Assets | C61: 0.14 | D61: 0.11 | E61: 0.18 | F61: 0.13 | G61: 0.09 | H61: Total debt / total assets
B62: Return on Equity (ROE %) | C62: -0.04 | D62: 0.02 | E62: -0.04 | F62: 0.12 | G62: 0.24 | H62: Net income / average shareholders' equity
B63: Return on Assets (ROA %) | C63: 0.058 | D63: 0.012 | E63: -0.023 | F63: 0.065 | G63: 0.138 | H63: Net income / average total assets
B64: Book Value per Share ($) | C64: 80.75 | D64: 76.1 | E64: 70.42 | F64: 72.43 | G64: 82.1 | H64: Total equity / diluted shares outstanding
A66: Source: Bloomberg Terminal, 02/10/2026, CVX US Equity | Blue = hardcoded inputs from Bloomberg | Figures in USD millions
